Metadata-Version: 2.1
Name: anybomt
Version: 0.1.1
Summary: Uma biblioteca para facilitar sua jornada em matemática
Author: AnyBoMath
Author-email: bidjorys@gmail.com
License: MIT
Classifier: Programming Language :: Python :: 3
Classifier: License :: OSI Approved :: MIT License
Classifier: Operating System :: OS Independent
Requires-Python: >=3.6
License-File: LICENSE
